paddlelabel/__init__.py
paddlelabel/__main__.py
paddlelabel/alembic.ini
paddlelabel/config.py
paddlelabel/default_setting.json
paddlelabel/openapi.yml
paddlelabel/serve.py
paddlelabel/util.py
paddlelabel/version
paddlelabel/api/__init__.py
paddlelabel/api/util.py
paddlelabel/api/controller/__init__.py
paddlelabel/api/controller/annotation.py
paddlelabel/api/controller/base.py
paddlelabel/api/controller/data.py
paddlelabel/api/controller/label.py
paddlelabel/api/controller/project.py
paddlelabel/api/controller/sample.py
paddlelabel/api/controller/setting.py
paddlelabel/api/controller/tag.py
paddlelabel/api/controller/task.py
paddlelabel/api/controller/user.py
paddlelabel/api/model/__init__.py
paddlelabel/api/model/annotation.py
paddlelabel/api/model/base.py
paddlelabel/api/model/data.py
paddlelabel/api/model/label.py
paddlelabel/api/model/project.py
paddlelabel/api/model/setting.py
paddlelabel/api/model/tag.py
paddlelabel/api/model/tag_task.py
paddlelabel/api/model/task.py
paddlelabel/api/model/user.py
paddlelabel/api/rpc/__init__.py
paddlelabel/api/rpc/cache.py
paddlelabel/api/rpc/debug.py
paddlelabel/api/rpc/file.py
paddlelabel/api/rpc/monitor.py
paddlelabel/api/rpc/seg.py
paddlelabel/api/rpc/util/__init__.py
paddlelabel/api/rpc/util/polygon.py
paddlelabel/api/schema/__init__.py
paddlelabel/api/schema/annotation.py
paddlelabel/api/schema/base.py
paddlelabel/api/schema/data.py
paddlelabel/api/schema/label.py
paddlelabel/api/schema/project.py
paddlelabel/api/schema/setting.py
paddlelabel/api/schema/tag.py
paddlelabel/api/schema/tag_task.py
paddlelabel/api/schema/task.py
paddlelabel/api/schema/user.py
paddlelabel/api/schema/util.py
paddlelabel/dbmigration/__init__.py
paddlelabel/dbmigration/env.py
paddlelabel/dbmigration/script.py.mako
paddlelabel/dbmigration/versions/23c1bf9b7f48_v0_1_2.py
paddlelabel/dbmigration/versions/61968cbf48e8_v0_1_3.py
paddlelabel/dbmigration/versions/__init__.py
paddlelabel/dbmigration/versions/a609821ce310_v0_1_4.py
paddlelabel-1.0.1.dist-info/LICENSE
paddlelabel-1.0.1.dist-info/METADATA
paddlelabel-1.0.1.dist-info/WHEEL
paddlelabel-1.0.1.dist-info/entry_points.txt
paddlelabel-1.0.1.dist-info/top_level.txt
paddlelabel-1.0.1.dist-info/RECORD
