Metadata-Version: 2.1
Name: paddlelabel
Version: 1.0.1
Summary: Web Based Multi Purpose Annotation Software
Home-page: https://github.com/PaddleCV-SIG/PaddleLabel
Author: PaddleCV-SIG
Author-email: me@linhan.email
License: Apache Software License
Classifier: License :: OSI Approved :: Apache Software License
Classifier: Programming Language :: Python :: 3
Classifier: Programming Language :: Python :: 3.9
License-File: LICENSE
Requires-Dist: connexion
Requires-Dist: marshmallow-sqlalchemy
Requires-Dist: flask-sqlalchemy
Requires-Dist: flask-marshmallow
Requires-Dist: flask-cors
Requires-Dist: opencv-python
Requires-Dist: numpy
Requires-Dist: pycocotoolse
Requires-Dist: tqdm
Requires-Dist: tifffile
Requires-Dist: alembic
Requires-Dist: prompt-toolkit
